{"nodes": [{"id": "users_caiosoares_nexus_sirius_projects_unlarp_cli_internal_ui_dirpicker_go", "label": "dirpicker.go", "file_type": "code", "source_file": "internal/ui/dirpicker.go", "source_location": "L1"}, {"id": "ui_dirpicker", "label": "DirPicker", "file_type": "code", "source_file": "internal/ui/dirpicker.go", "source_location": "L19"}, {"id": "client", "label": "Client", "file_type": "code", "source_file": "internal/ui/dirpicker.go", "source_location": "L21"}, {"id": "model", "label": "Model", "file_type": "code", "source_file": "internal/ui/dirpicker.go", "source_location": "L30"}, {"id": "ui_dirpicker_newdirpicker", "label": "NewDirPicker()", "file_type": "code", "source_file": "internal/ui/dirpicker.go", "source_location": "L40"}, {"id": "ui_dirpicker_init", "label": ".Init()", "file_type": "code", "source_file": "internal/ui/dirpicker.go", "source_location": "L73"}, {"id": "cmd", "label": "Cmd", "file_type": "code", "source_file": "internal/ui/dirpicker.go", "source_location": "L73"}, {"id": "ui_dirpicker_refreshdirs", "label": ".refreshDirs()", "file_type": "code", "source_file": "internal/ui/dirpicker.go", "source_location": "L77"}, {"id": "ui_dirpicker_update", "label": ".Update()", "file_type": "code", "source_file": "internal/ui/dirpicker.go", "source_location": "L119"}, {"id": "msg", "label": "Msg", "file_type": "code", "source_file": "internal/ui/dirpicker.go", "source_location": "L119"}, {"id": "ui_dirpicker_view", "label": ".View()", "file_type": "code", "source_file": "internal/ui/dirpicker.go", "source_location": "L247"}, {"id": "ui_dirpicker_chooselocaldir", "label": "ChooseLocalDir()", "file_type": "code", "source_file": "internal/ui/dirpicker.go", "source_location": "L313"}, {"id": "ui_dirpicker_chooseremotedir", "label": "ChooseRemoteDir()", "file_type": "code", "source_file": "internal/ui/dirpicker.go", "source_location": "L328"}], "edges": [{"source": "users_caiosoares_nexus_sirius_projects_unlarp_cli_internal_ui_dirpicker_go", "target": "go_pkg_fmt", "relation": "imports_from", "confidence": "EXTRACTED", "source_file": "internal/ui/dirpicker.go", "source_location": "L4", "weight": 1.0, "context": "import"}, {"source": "users_caiosoares_nexus_sirius_projects_unlarp_cli_internal_ui_dirpicker_go", "target": "go_pkg_os", "relation": "imports_from", "confidence": "EXTRACTED", "source_file": "internal/ui/dirpicker.go", "source_location": "L5", "weight": 1.0, "context": "import"}, {"source": "users_caiosoares_nexus_sirius_projects_unlarp_cli_internal_ui_dirpicker_go", "target": "go_pkg_path", "relation": "imports_from", "confidence": "EXTRACTED", "source_file": "internal/ui/dirpicker.go", "source_location": "L6", "weight": 1.0, "context": "import"}, {"source": "users_caiosoares_nexus_sirius_projects_unlarp_cli_internal_ui_dirpicker_go", "target": "go_pkg_path_filepath", "relation": "imports_from", "confidence": "EXTRACTED", "source_file": "internal/ui/dirpicker.go", "source_location": "L7", "weight": 1.0, "context": "import"}, {"source": "users_caiosoares_nexus_sirius_projects_unlarp_cli_internal_ui_dirpicker_go", "target": "go_pkg_sort", "relation": "imports_from", "confidence": "EXTRACTED", "source_file": "internal/ui/dirpicker.go", "source_location": "L8", "weight": 1.0, "context": "import"}, {"source": "users_caiosoares_nexus_sirius_projects_unlarp_cli_internal_ui_dirpicker_go", "target": "go_pkg_strings", "relation": "imports_from", "confidence": "EXTRACTED", "source_file": "internal/ui/dirpicker.go", "source_location": "L9", "weight": 1.0, "context": "import"}, {"source": "users_caiosoares_nexus_sirius_projects_unlarp_cli_internal_ui_dirpicker_go", "target": "go_pkg_github_com_charmbracelet_bubbles_textinput", "relation": "imports_from", "confidence": "EXTRACTED", "source_file": "internal/ui/dirpicker.go", "source_location": "L11", "weight": 1.0, "context": "import"}, {"source": "users_caiosoares_nexus_sirius_projects_unlarp_cli_internal_ui_dirpicker_go", "target": "go_pkg_github_com_charmbracelet_bubbletea", "relation": "imports_from", "confidence": "EXTRACTED", "source_file": "internal/ui/dirpicker.go", "source_location": "L12", "weight": 1.0, "context": "import"}, {"source": "users_caiosoares_nexus_sirius_projects_unlarp_cli_internal_ui_dirpicker_go", "target": "go_pkg_github_com_charmbracelet_lipgloss", "relation": "imports_from", "confidence": "EXTRACTED", "source_file": "internal/ui/dirpicker.go", "source_location": "L13", "weight": 1.0, "context": "import"}, {"source": "users_caiosoares_nexus_sirius_projects_unlarp_cli_internal_ui_dirpicker_go", "target": "go_pkg_github_com_pkg_sftp", "relation": "imports_from", "confidence": "EXTRACTED", "source_file": "internal/ui/dirpicker.go", "source_location": "L14", "weight": 1.0, "context": "import"}, {"source": "users_caiosoares_nexus_sirius_projects_unlarp_cli_internal_ui_dirpicker_go", "target": "go_pkg_github_com_caiofasoares_unlarp_internal_tui_styles", "relation": "imports_from", "confidence": "EXTRACTED", "source_file": "internal/ui/dirpicker.go", "source_location": "L16", "weight": 1.0, "context": "import"}, {"source": "users_caiosoares_nexus_sirius_projects_unlarp_cli_internal_ui_dirpicker_go", "target": "ui_dirpicker", "relation": "contains", "confidence": "EXTRACTED", "source_file": "internal/ui/dirpicker.go", "source_location": "L19", "weight": 1.0}, {"source": "ui_dirpicker", "target": "client", "relation": "references", "confidence": "EXTRACTED", "source_file": "internal/ui/dirpicker.go", "source_location": "L21", "weight": 1.0, "context": "field"}, {"source": "ui_dirpicker", "target": "model", "relation": "references", "confidence": "EXTRACTED", "source_file": "internal/ui/dirpicker.go", "source_location": "L30", "weight": 1.0, "context": "field"}, {"source": "ui_dirpicker", "target": "model", "relation": "references", "confidence": "EXTRACTED", "source_file": "internal/ui/dirpicker.go", "source_location": "L33", "weight": 1.0, "context": "field"}, {"source": "users_caiosoares_nexus_sirius_projects_unlarp_cli_internal_ui_dirpicker_go", "target": "ui_dirpicker_newdirpicker", "relation": "contains", "confidence": "EXTRACTED", "source_file": "internal/ui/dirpicker.go", "source_location": "L40", "weight": 1.0}, {"source": "ui_dirpicker_newdirpicker", "target": "client", "relation": "references", "confidence": "EXTRACTED", "source_file": "internal/ui/dirpicker.go", "source_location": "L40", "weight": 1.0, "context": "parameter_type"}, {"source": "ui_dirpicker_newdirpicker", "target": "ui_dirpicker", "relation": "references", "confidence": "EXTRACTED", "source_file": "internal/ui/dirpicker.go", "source_location": "L40", "weight": 1.0, "context": "return_type"}, {"source": "ui_dirpicker", "target": "ui_dirpicker_init", "relation": "method", "confidence": "EXTRACTED", "source_file": "internal/ui/dirpicker.go", "source_location": "L73", "weight": 1.0}, {"source": "ui_dirpicker_init", "target": "cmd", "relation": "references", "confidence": "EXTRACTED", "source_file": "internal/ui/dirpicker.go", "source_location": "L73", "weight": 1.0, "context": "return_type"}, {"source": "ui_dirpicker", "target": "ui_dirpicker_refreshdirs", "relation": "method", "confidence": "EXTRACTED", "source_file": "internal/ui/dirpicker.go", "source_location": "L77", "weight": 1.0}, {"source": "ui_dirpicker", "target": "ui_dirpicker_update", "relation": "method", "confidence": "EXTRACTED", "source_file": "internal/ui/dirpicker.go", "source_location": "L119", "weight": 1.0}, {"source": "ui_dirpicker_update", "target": "msg", "relation": "references", "confidence": "EXTRACTED", "source_file": "internal/ui/dirpicker.go", "source_location": "L119", "weight": 1.0, "context": "parameter_type"}, {"source": "ui_dirpicker_update", "target": "model", "relation": "references", "confidence": "EXTRACTED", "source_file": "internal/ui/dirpicker.go", "source_location": "L119", "weight": 1.0, "context": "return_type"}, {"source": "ui_dirpicker_update", "target": "cmd", "relation": "references", "confidence": "EXTRACTED", "source_file": "internal/ui/dirpicker.go", "source_location": "L119", "weight": 1.0, "context": "return_type"}, {"source": "ui_dirpicker", "target": "ui_dirpicker_view", "relation": "method", "confidence": "EXTRACTED", "source_file": "internal/ui/dirpicker.go", "source_location": "L247", "weight": 1.0}, {"source": "users_caiosoares_nexus_sirius_projects_unlarp_cli_internal_ui_dirpicker_go", "target": "ui_dirpicker_chooselocaldir", "relation": "contains", "confidence": "EXTRACTED", "source_file": "internal/ui/dirpicker.go", "source_location": "L313", "weight": 1.0}, {"source": "users_caiosoares_nexus_sirius_projects_unlarp_cli_internal_ui_dirpicker_go", "target": "ui_dirpicker_chooseremotedir", "relation": "contains", "confidence": "EXTRACTED", "source_file": "internal/ui/dirpicker.go", "source_location": "L328", "weight": 1.0}, {"source": "ui_dirpicker_chooseremotedir", "target": "client", "relation": "references", "confidence": "EXTRACTED", "source_file": "internal/ui/dirpicker.go", "source_location": "L328", "weight": 1.0, "context": "parameter_type"}, {"source": "ui_dirpicker_newdirpicker", "target": "ui_dirpicker_refreshdirs", "relation": "calls", "context": "call", "confidence": "EXTRACTED", "source_file": "internal/ui/dirpicker.go", "source_location": "L69", "weight": 1.0}, {"source": "ui_dirpicker_update", "target": "ui_dirpicker_refreshdirs", "relation": "calls", "context": "call", "confidence": "EXTRACTED", "source_file": "internal/ui/dirpicker.go", "source_location": "L135", "weight": 1.0}, {"source": "ui_dirpicker_chooselocaldir", "target": "ui_dirpicker_newdirpicker", "relation": "calls", "context": "call", "confidence": "EXTRACTED", "source_file": "internal/ui/dirpicker.go", "source_location": "L314", "weight": 1.0}, {"source": "ui_dirpicker_chooseremotedir", "target": "ui_dirpicker_newdirpicker", "relation": "calls", "context": "call", "confidence": "EXTRACTED", "source_file": "internal/ui/dirpicker.go", "source_location": "L329", "weight": 1.0}], "raw_calls": [{"caller_nid": "ui_dirpicker_newdirpicker", "callee": "Abs", "is_member_call": false, "source_file": "/Users/caiosoares/_Nexus/sirius/Projects/Unlarp/cli/internal/ui/dirpicker.go", "source_location": "L44"}, {"caller_nid": "ui_dirpicker_newdirpicker", "callee": "New", "is_member_call": false, "source_file": "/Users/caiosoares/_Nexus/sirius/Projects/Unlarp/cli/internal/ui/dirpicker.go", "source_location": "L52"}, {"caller_nid": "ui_dirpicker_newdirpicker", "callee": "New", "is_member_call": false, "source_file": "/Users/caiosoares/_Nexus/sirius/Projects/Unlarp/cli/internal/ui/dirpicker.go", "source_location": "L57"}, {"caller_nid": "ui_dirpicker_refreshdirs", "callee": "Errorf", "is_member_call": false, "source_file": "/Users/caiosoares/_Nexus/sirius/Projects/Unlarp/cli/internal/ui/dirpicker.go", "source_location": "L83"}, {"caller_nid": "ui_dirpicker_refreshdirs", "callee": "ReadDir", "is_member_call": true, "source_file": "/Users/caiosoares/_Nexus/sirius/Projects/Unlarp/cli/internal/ui/dirpicker.go", "source_location": "L86"}, {"caller_nid": "ui_dirpicker_refreshdirs", "callee": "IsDir", "is_member_call": true, "source_file": "/Users/caiosoares/_Nexus/sirius/Projects/Unlarp/cli/internal/ui/dirpicker.go", "source_location": "L92"}, {"caller_nid": "ui_dirpicker_refreshdirs", "callee": "Name", "is_member_call": true, "source_file": "/Users/caiosoares/_Nexus/sirius/Projects/Unlarp/cli/internal/ui/dirpicker.go", "source_location": "L93"}, {"caller_nid": "ui_dirpicker_refreshdirs", "callee": "append", "is_member_call": false, "source_file": "/Users/caiosoares/_Nexus/sirius/Projects/Unlarp/cli/internal/ui/dirpicker.go", "source_location": "L95"}, {"caller_nid": "ui_dirpicker_refreshdirs", "callee": "ReadDir", "is_member_call": false, "source_file": "/Users/caiosoares/_Nexus/sirius/Projects/Unlarp/cli/internal/ui/dirpicker.go", "source_location": "L100"}, {"caller_nid": "ui_dirpicker_refreshdirs", "callee": "IsDir", "is_member_call": true, "source_file": "/Users/caiosoares/_Nexus/sirius/Projects/Unlarp/cli/internal/ui/dirpicker.go", "source_location": "L106"}, {"caller_nid": "ui_dirpicker_refreshdirs", "callee": "Name", "is_member_call": true, "source_file": "/Users/caiosoares/_Nexus/sirius/Projects/Unlarp/cli/internal/ui/dirpicker.go", "source_location": "L107"}, {"caller_nid": "ui_dirpicker_refreshdirs", "callee": "HasPrefix", "is_member_call": false, "source_file": "/Users/caiosoares/_Nexus/sirius/Projects/Unlarp/cli/internal/ui/dirpicker.go", "source_location": "L108"}, {"caller_nid": "ui_dirpicker_refreshdirs", "callee": "append", "is_member_call": false, "source_file": "/Users/caiosoares/_Nexus/sirius/Projects/Unlarp/cli/internal/ui/dirpicker.go", "source_location": "L109"}, {"caller_nid": "ui_dirpicker_refreshdirs", "callee": "Strings", "is_member_call": false, "source_file": "/Users/caiosoares/_Nexus/sirius/Projects/Unlarp/cli/internal/ui/dirpicker.go", "source_location": "L115"}, {"caller_nid": "ui_dirpicker_update", "callee": "TrimSpace", "is_member_call": false, "source_file": "/Users/caiosoares/_Nexus/sirius/Projects/Unlarp/cli/internal/ui/dirpicker.go", "source_location": "L127"}, {"caller_nid": "ui_dirpicker_update", "callee": "Value", "is_member_call": true, "source_file": "/Users/caiosoares/_Nexus/sirius/Projects/Unlarp/cli/internal/ui/dirpicker.go", "source_location": "L127"}, {"caller_nid": "ui_dirpicker_update", "callee": "Clean", "is_member_call": false, "source_file": "/Users/caiosoares/_Nexus/sirius/Projects/Unlarp/cli/internal/ui/dirpicker.go", "source_location": "L130"}, {"caller_nid": "ui_dirpicker_update", "callee": "Clean", "is_member_call": false, "source_file": "/Users/caiosoares/_Nexus/sirius/Projects/Unlarp/cli/internal/ui/dirpicker.go", "source_location": "L132"}, {"caller_nid": "ui_dirpicker_update", "callee": "Update", "is_member_call": true, "source_file": "/Users/caiosoares/_Nexus/sirius/Projects/Unlarp/cli/internal/ui/dirpicker.go", "source_location": "L140"}, {"caller_nid": "ui_dirpicker_update", "callee": "TrimSpace", "is_member_call": false, "source_file": "/Users/caiosoares/_Nexus/sirius/Projects/Unlarp/cli/internal/ui/dirpicker.go", "source_location": "L152"}, {"caller_nid": "ui_dirpicker_update", "callee": "Value", "is_member_call": true, "source_file": "/Users/caiosoares/_Nexus/sirius/Projects/Unlarp/cli/internal/ui/dirpicker.go", "source_location": "L152"}, {"caller_nid": "ui_dirpicker_update", "callee": "Join", "is_member_call": false, "source_file": "/Users/caiosoares/_Nexus/sirius/Projects/Unlarp/cli/internal/ui/dirpicker.go", "source_location": "L156"}, {"caller_nid": "ui_dirpicker_update", "callee": "Mkdir", "is_member_call": true, "source_file": "/Users/caiosoares/_Nexus/sirius/Projects/Unlarp/cli/internal/ui/dirpicker.go", "source_location": "L157"}, {"caller_nid": "ui_dirpicker_update", "callee": "Join", "is_member_call": false, "source_file": "/Users/caiosoares/_Nexus/sirius/Projects/Unlarp/cli/internal/ui/dirpicker.go", "source_location": "L165"}, {"caller_nid": "ui_dirpicker_update", "callee": "Mkdir", "is_member_call": false, "source_file": "/Users/caiosoares/_Nexus/sirius/Projects/Unlarp/cli/internal/ui/dirpicker.go", "source_location": "L166"}, {"caller_nid": "ui_dirpicker_update", "callee": "Update", "is_member_call": true, "source_file": "/Users/caiosoares/_Nexus/sirius/Projects/Unlarp/cli/internal/ui/dirpicker.go", "source_location": "L179"}, {"caller_nid": "ui_dirpicker_update", "callee": "Join", "is_member_call": false, "source_file": "/Users/caiosoares/_Nexus/sirius/Projects/Unlarp/cli/internal/ui/dirpicker.go", "source_location": "L201"}, {"caller_nid": "ui_dirpicker_update", "callee": "Join", "is_member_call": false, "source_file": "/Users/caiosoares/_Nexus/sirius/Projects/Unlarp/cli/internal/ui/dirpicker.go", "source_location": "L203"}, {"caller_nid": "ui_dirpicker_update", "callee": "Dir", "is_member_call": false, "source_file": "/Users/caiosoares/_Nexus/sirius/Projects/Unlarp/cli/internal/ui/dirpicker.go", "source_location": "L210"}, {"caller_nid": "ui_dirpicker_update", "callee": "Dir", "is_member_call": false, "source_file": "/Users/caiosoares/_Nexus/sirius/Projects/Unlarp/cli/internal/ui/dirpicker.go", "source_location": "L212"}, {"caller_nid": "ui_dirpicker_update", "callee": "SetValue", "is_member_call": true, "source_file": "/Users/caiosoares/_Nexus/sirius/Projects/Unlarp/cli/internal/ui/dirpicker.go", "source_location": "L227"}, {"caller_nid": "ui_dirpicker_update", "callee": "Focus", "is_member_call": true, "source_file": "/Users/caiosoares/_Nexus/sirius/Projects/Unlarp/cli/internal/ui/dirpicker.go", "source_location": "L228"}, {"caller_nid": "ui_dirpicker_update", "callee": "SetValue", "is_member_call": true, "source_file": "/Users/caiosoares/_Nexus/sirius/Projects/Unlarp/cli/internal/ui/dirpicker.go", "source_location": "L232"}, {"caller_nid": "ui_dirpicker_update", "callee": "Focus", "is_member_call": true, "source_file": "/Users/caiosoares/_Nexus/sirius/Projects/Unlarp/cli/internal/ui/dirpicker.go", "source_location": "L233"}, {"caller_nid": "ui_dirpicker_view", "callee": "WriteString", "is_member_call": true, "source_file": "/Users/caiosoares/_Nexus/sirius/Projects/Unlarp/cli/internal/ui/dirpicker.go", "source_location": "L255"}, {"caller_nid": "ui_dirpicker_view", "callee": "Render", "is_member_call": true, "source_file": "/Users/caiosoares/_Nexus/sirius/Projects/Unlarp/cli/internal/ui/dirpicker.go", "source_location": "L255"}, {"caller_nid": "ui_dirpicker_view", "callee": "Sprintf", "is_member_call": false, "source_file": "/Users/caiosoares/_Nexus/sirius/Projects/Unlarp/cli/internal/ui/dirpicker.go", "source_location": "L255"}, {"caller_nid": "ui_dirpicker_view", "callee": "WriteString", "is_member_call": true, "source_file": "/Users/caiosoares/_Nexus/sirius/Projects/Unlarp/cli/internal/ui/dirpicker.go", "source_location": "L256"}, {"caller_nid": "ui_dirpicker_view", "callee": "WriteString", "is_member_call": true, "source_file": "/Users/caiosoares/_Nexus/sirius/Projects/Unlarp/cli/internal/ui/dirpicker.go", "source_location": "L258"}, {"caller_nid": "ui_dirpicker_view", "callee": "Render", "is_member_call": true, "source_file": "/Users/caiosoares/_Nexus/sirius/Projects/Unlarp/cli/internal/ui/dirpicker.go", "source_location": "L258"}, {"caller_nid": "ui_dirpicker_view", "callee": "WriteString", "is_member_call": true, "source_file": "/Users/caiosoares/_Nexus/sirius/Projects/Unlarp/cli/internal/ui/dirpicker.go", "source_location": "L259"}, {"caller_nid": "ui_dirpicker_view", "callee": "Render", "is_member_call": true, "source_file": "/Users/caiosoares/_Nexus/sirius/Projects/Unlarp/cli/internal/ui/dirpicker.go", "source_location": "L259"}, {"caller_nid": "ui_dirpicker_view", "callee": "WriteString", "is_member_call": true, "source_file": "/Users/caiosoares/_Nexus/sirius/Projects/Unlarp/cli/internal/ui/dirpicker.go", "source_location": "L260"}, {"caller_nid": "ui_dirpicker_view", "callee": "WriteString", "is_member_call": true, "source_file": "/Users/caiosoares/_Nexus/sirius/Projects/Unlarp/cli/internal/ui/dirpicker.go", "source_location": "L263"}, {"caller_nid": "ui_dirpicker_view", "callee": "WriteString", "is_member_call": true, "source_file": "/Users/caiosoares/_Nexus/sirius/Projects/Unlarp/cli/internal/ui/dirpicker.go", "source_location": "L264"}, {"caller_nid": "ui_dirpicker_view", "callee": "View", "is_member_call": true, "source_file": "/Users/caiosoares/_Nexus/sirius/Projects/Unlarp/cli/internal/ui/dirpicker.go", "source_location": "L264"}, {"caller_nid": "ui_dirpicker_view", "callee": "WriteString", "is_member_call": true, "source_file": "/Users/caiosoares/_Nexus/sirius/Projects/Unlarp/cli/internal/ui/dirpicker.go", "source_location": "L265"}, {"caller_nid": "ui_dirpicker_view", "callee": "WriteString", "is_member_call": true, "source_file": "/Users/caiosoares/_Nexus/sirius/Projects/Unlarp/cli/internal/ui/dirpicker.go", "source_location": "L270"}, {"caller_nid": "ui_dirpicker_view", "callee": "WriteString", "is_member_call": true, "source_file": "/Users/caiosoares/_Nexus/sirius/Projects/Unlarp/cli/internal/ui/dirpicker.go", "source_location": "L271"}, {"caller_nid": "ui_dirpicker_view", "callee": "View", "is_member_call": true, "source_file": "/Users/caiosoares/_Nexus/sirius/Projects/Unlarp/cli/internal/ui/dirpicker.go", "source_location": "L271"}, {"caller_nid": "ui_dirpicker_view", "callee": "WriteString", "is_member_call": true, "source_file": "/Users/caiosoares/_Nexus/sirius/Projects/Unlarp/cli/internal/ui/dirpicker.go", "source_location": "L272"}, {"caller_nid": "ui_dirpicker_view", "callee": "WriteString", "is_member_call": true, "source_file": "/Users/caiosoares/_Nexus/sirius/Projects/Unlarp/cli/internal/ui/dirpicker.go", "source_location": "L277"}, {"caller_nid": "ui_dirpicker_view", "callee": "Render", "is_member_call": true, "source_file": "/Users/caiosoares/_Nexus/sirius/Projects/Unlarp/cli/internal/ui/dirpicker.go", "source_location": "L277"}, {"caller_nid": "ui_dirpicker_view", "callee": "Foreground", "is_member_call": true, "source_file": "/Users/caiosoares/_Nexus/sirius/Projects/Unlarp/cli/internal/ui/dirpicker.go", "source_location": "L277"}, {"caller_nid": "ui_dirpicker_view", "callee": "NewStyle", "is_member_call": false, "source_file": "/Users/caiosoares/_Nexus/sirius/Projects/Unlarp/cli/internal/ui/dirpicker.go", "source_location": "L277"}, {"caller_nid": "ui_dirpicker_view", "callee": "Sprintf", "is_member_call": false, "source_file": "/Users/caiosoares/_Nexus/sirius/Projects/Unlarp/cli/internal/ui/dirpicker.go", "source_location": "L277"}, {"caller_nid": "ui_dirpicker_view", "callee": "WriteString", "is_member_call": true, "source_file": "/Users/caiosoares/_Nexus/sirius/Projects/Unlarp/cli/internal/ui/dirpicker.go", "source_location": "L278"}, {"caller_nid": "ui_dirpicker_view", "callee": "WriteString", "is_member_call": true, "source_file": "/Users/caiosoares/_Nexus/sirius/Projects/Unlarp/cli/internal/ui/dirpicker.go", "source_location": "L281"}, {"caller_nid": "ui_dirpicker_view", "callee": "WriteString", "is_member_call": true, "source_file": "/Users/caiosoares/_Nexus/sirius/Projects/Unlarp/cli/internal/ui/dirpicker.go", "source_location": "L283"}, {"caller_nid": "ui_dirpicker_view", "callee": "Render", "is_member_call": true, "source_file": "/Users/caiosoares/_Nexus/sirius/Projects/Unlarp/cli/internal/ui/dirpicker.go", "source_location": "L283"}, {"caller_nid": "ui_dirpicker_view", "callee": "Foreground", "is_member_call": true, "source_file": "/Users/caiosoares/_Nexus/sirius/Projects/Unlarp/cli/internal/ui/dirpicker.go", "source_location": "L283"}, {"caller_nid": "ui_dirpicker_view", "callee": "NewStyle", "is_member_call": false, "source_file": "/Users/caiosoares/_Nexus/sirius/Projects/Unlarp/cli/internal/ui/dirpicker.go", "source_location": "L283"}, {"caller_nid": "ui_dirpicker_view", "callee": "WriteString", "is_member_call": true, "source_file": "/Users/caiosoares/_Nexus/sirius/Projects/Unlarp/cli/internal/ui/dirpicker.go", "source_location": "L284"}, {"caller_nid": "ui_dirpicker_view", "callee": "Sprintf", "is_member_call": false, "source_file": "/Users/caiosoares/_Nexus/sirius/Projects/Unlarp/cli/internal/ui/dirpicker.go", "source_location": "L287"}, {"caller_nid": "ui_dirpicker_view", "callee": "WriteString", "is_member_call": true, "source_file": "/Users/caiosoares/_Nexus/sirius/Projects/Unlarp/cli/internal/ui/dirpicker.go", "source_location": "L289"}, {"caller_nid": "ui_dirpicker_view", "callee": "Render", "is_member_call": true, "source_file": "/Users/caiosoares/_Nexus/sirius/Projects/Unlarp/cli/internal/ui/dirpicker.go", "source_location": "L289"}, {"caller_nid": "ui_dirpicker_view", "callee": "WriteString", "is_member_call": true, "source_file": "/Users/caiosoares/_Nexus/sirius/Projects/Unlarp/cli/internal/ui/dirpicker.go", "source_location": "L291"}, {"caller_nid": "ui_dirpicker_view", "callee": "WriteString", "is_member_call": true, "source_file": "/Users/caiosoares/_Nexus/sirius/Projects/Unlarp/cli/internal/ui/dirpicker.go", "source_location": "L293"}, {"caller_nid": "ui_dirpicker_view", "callee": "WriteString", "is_member_call": true, "source_file": "/Users/caiosoares/_Nexus/sirius/Projects/Unlarp/cli/internal/ui/dirpicker.go", "source_location": "L297"}, {"caller_nid": "ui_dirpicker_view", "callee": "WriteString", "is_member_call": true, "source_file": "/Users/caiosoares/_Nexus/sirius/Projects/Unlarp/cli/internal/ui/dirpicker.go", "source_location": "L298"}, {"caller_nid": "ui_dirpicker_view", "callee": "Render", "is_member_call": true, "source_file": "/Users/caiosoares/_Nexus/sirius/Projects/Unlarp/cli/internal/ui/dirpicker.go", "source_location": "L298"}, {"caller_nid": "ui_dirpicker_view", "callee": "Sprintf", "is_member_call": false, "source_file": "/Users/caiosoares/_Nexus/sirius/Projects/Unlarp/cli/internal/ui/dirpicker.go", "source_location": "L299"}, {"caller_nid": "ui_dirpicker_view", "callee": "Render", "is_member_call": true, "source_file": "/Users/caiosoares/_Nexus/sirius/Projects/Unlarp/cli/internal/ui/dirpicker.go", "source_location": "L300"}, {"caller_nid": "ui_dirpicker_view", "callee": "Render", "is_member_call": true, "source_file": "/Users/caiosoares/_Nexus/sirius/Projects/Unlarp/cli/internal/ui/dirpicker.go", "source_location": "L301"}, {"caller_nid": "ui_dirpicker_view", "callee": "Render", "is_member_call": true, "source_file": "/Users/caiosoares/_Nexus/sirius/Projects/Unlarp/cli/internal/ui/dirpicker.go", "source_location": "L302"}, {"caller_nid": "ui_dirpicker_view", "callee": "Render", "is_member_call": true, "source_file": "/Users/caiosoares/_Nexus/sirius/Projects/Unlarp/cli/internal/ui/dirpicker.go", "source_location": "L303"}, {"caller_nid": "ui_dirpicker_view", "callee": "Render", "is_member_call": true, "source_file": "/Users/caiosoares/_Nexus/sirius/Projects/Unlarp/cli/internal/ui/dirpicker.go", "source_location": "L304"}, {"caller_nid": "ui_dirpicker_view", "callee": "Render", "is_member_call": true, "source_file": "/Users/caiosoares/_Nexus/sirius/Projects/Unlarp/cli/internal/ui/dirpicker.go", "source_location": "L305"}, {"caller_nid": "ui_dirpicker_view", "callee": "Render", "is_member_call": true, "source_file": "/Users/caiosoares/_Nexus/sirius/Projects/Unlarp/cli/internal/ui/dirpicker.go", "source_location": "L306"}, {"caller_nid": "ui_dirpicker_chooselocaldir", "callee": "NewProgram", "is_member_call": false, "source_file": "/Users/caiosoares/_Nexus/sirius/Projects/Unlarp/cli/internal/ui/dirpicker.go", "source_location": "L316"}, {"caller_nid": "ui_dirpicker_chooselocaldir", "callee": "WithAltScreen", "is_member_call": false, "source_file": "/Users/caiosoares/_Nexus/sirius/Projects/Unlarp/cli/internal/ui/dirpicker.go", "source_location": "L316"}, {"caller_nid": "ui_dirpicker_chooselocaldir", "callee": "Run", "is_member_call": true, "source_file": "/Users/caiosoares/_Nexus/sirius/Projects/Unlarp/cli/internal/ui/dirpicker.go", "source_location": "L317"}, {"caller_nid": "ui_dirpicker_chooselocaldir", "callee": "Errorf", "is_member_call": false, "source_file": "/Users/caiosoares/_Nexus/sirius/Projects/Unlarp/cli/internal/ui/dirpicker.go", "source_location": "L323"}, {"caller_nid": "ui_dirpicker_chooseremotedir", "callee": "NewProgram", "is_member_call": false, "source_file": "/Users/caiosoares/_Nexus/sirius/Projects/Unlarp/cli/internal/ui/dirpicker.go", "source_location": "L331"}, {"caller_nid": "ui_dirpicker_chooseremotedir", "callee": "WithAltScreen", "is_member_call": false, "source_file": "/Users/caiosoares/_Nexus/sirius/Projects/Unlarp/cli/internal/ui/dirpicker.go", "source_location": "L331"}, {"caller_nid": "ui_dirpicker_chooseremotedir", "callee": "Run", "is_member_call": true, "source_file": "/Users/caiosoares/_Nexus/sirius/Projects/Unlarp/cli/internal/ui/dirpicker.go", "source_location": "L332"}, {"caller_nid": "ui_dirpicker_chooseremotedir", "callee": "Errorf", "is_member_call": false, "source_file": "/Users/caiosoares/_Nexus/sirius/Projects/Unlarp/cli/internal/ui/dirpicker.go", "source_location": "L338"}]}